{
 "__onload": {
  "print_templates": []
 },
 "__unsaved": 1,
 "absolute_value": 0,
 "align_labels_right": 0,
 "creation": "2024-05-07 17:56:54.393025",
 "css": ":root { --scale-factor: 0.8999999761581421px; --modal-x: 0px; --modal-y: 0px; } .staticText { display: inline-block; font-family: Inter; font-size: 14px; font-weight: 400; color: rgb(0, 0, 0); text-align: left; font-style: normal; text-decoration: none; text-transform: none; line-height: 1.25; letter-spacing: 0px; border: 0px solid rgb(0, 0, 0); border-radius: 0px; padding: 0px; margin: 0px; min-width: 0px; min-height: 0px; box-shadow: none; overflow: hidden; overflow-wrap: break-word; white-space: normal; user-select: none; opacity: 1; z-index: 1; } .dynamicText { display: inline-block; font-family: Inter; font-size: 14px; font-weight: 400; color: rgb(0, 0, 0); text-align: left; font-style: normal; text-decoration: none; text-transform: none; line-height: 1.25; letter-spacing: 0px; border: 0px solid rgb(0, 0, 0); border-radius: 0px; padding: 0px; margin: 0px; min-width: 0px; min-height: 0px; box-shadow: none; overflow: hidden; overflow-wrap: break-word; white-space: normal; user-select: none; opacity: 1; } .dynamicText .label-text { font-family: Inter; font-size: 14px; font-weight: 600; color: rgb(0, 0, 0); text-align: left; font-style: normal; text-decoration: none; text-transform: none; line-height: 1.25; letter-spacing: 0px; border: 0px solid rgb(0, 0, 0); border-radius: 0px; padding: 0px; margin: 0px; min-width: 0px; min-height: 0px; box-shadow: none; white-space: normal; user-select: none; opacity: 1; z-index: 1; } .rectangle { padding: 0px; margin: 0px; white-space: normal; user-select: none; min-width: 0px; min-height: 0px; color: rgb(0, 0, 0); border: 1px solid rgb(0, 0, 0); box-sizing: border-box; outline: none; border-radius: 0px; box-shadow: none; opacity: 1; z-index: 0; } .image { display: block; border: 0px solid rgb(0, 0, 0); border-radius: 0px; padding: 0px; margin: 0px; min-width: 0px; min-height: 0px; box-shadow: none; white-space: normal; user-select: none; object-fit: scale-down; object-position: center center; background-size: contain; background-position: center center; background-repeat: no-repeat; opacity: 1; } .barcode { display: block; border: 0px solid rgb(0, 0, 0); border-radius: 0px; padding: 0px; margin: 0px; min-width: 0px; min-height: 0px; box-shadow: none; white-space: normal; user-select: none; opacity: 1; } .printTable td { font-family: Inter; font-size: 10px; font-weight: 400; color: rgb(0, 0, 0); text-align: left; font-style: normal; text-decoration: none; text-transform: none; line-height: 1.25; letter-spacing: 0px; border: 1px solid rgb(0, 0, 0); border-radius: 0px; background-color: rgb(255, 255, 255); padding: 10px; margin: 0px; min-width: 0px; min-height: 0px; box-shadow: none; overflow-wrap: break-word; white-space: normal; user-select: none; vertical-align: baseline; opacity: 1; } .printTable .label-text { font-family: Inter; font-size: 10px; font-weight: 600; color: rgb(0, 0, 0); text-align: left; font-style: normal; text-decoration: none; text-transform: none; line-height: 1.25; letter-spacing: 0px; border: 0px solid rgb(0, 0, 0); border-radius: 0px; background-color: rgb(255, 255, 255); padding: 0px; margin: 0px; min-width: 0px; min-height: 0px; box-shadow: none; white-space: normal; user-select: none; opacity: 1; vertical-align: baseline; z-index: 1; } .printTable th { font-family: Inter; font-size: 11px; font-weight: 600; color: rgb(0, 0, 0); text-align: left; font-style: normal; text-decoration: none; text-transform: none; line-height: 1.25; letter-spacing: 0px; border: 1px solid rgb(0, 0, 0); border-radius: 0px; background-color: rgb(255, 255, 255); padding: 10px; margin: 0px; min-width: 0px; min-height: 0px; box-shadow: none; white-space: normal; user-select: none; opacity: 1; z-index: 1; } .printTable tr:nth-child(2n) td { } :root, ::after, ::before { --print-width: 210.000mm; --print-height: 297.000mm; --print-container-width: 210.000mm; --print-container-height: 297.000mm; --print-margin-top: 0mm; --print-margin-bottom: 0.000mm; --print-margin-left: 0mm; --print-margin-right: 0.000mm; } :root, ::after, ::before { --print-width: 210.000mm; --print-height: 297.000mm; --print-container-width: 210.000mm; --print-container-height: 297.000mm; --print-margin-top: 0mm; --print-margin-bottom: 0.000mm; --print-margin-left: 0mm; --print-margin-right: 0.000mm; } :root { --scale-factor: 0.8999999761581421px; --modal-x: 0px; --modal-y: 0px; } :root, ::after, ::before { --print-width: 210.000mm; --print-height: 297.000mm; --print-container-width: 210.000mm; --print-container-height: 297.000mm; --print-margin-top: 0mm; --print-margin-bottom: 0.000mm; --print-margin-left: 0mm; --print-margin-right: 0.000mm; } :root, ::after, ::before { --print-width: 210.000mm; --print-height: 297.000mm; --print-container-width: 210.000mm; --print-container-height: 297.000mm; --print-margin-top: 0mm; --print-margin-bottom: 0.000mm; --print-margin-left: 0mm; --print-margin-right: 0.000mm; } :root, ::after, ::before { --print-width: 210.000mm; --print-height: 297.000mm; --print-container-width: 210.000mm; --print-container-height: 297.001mm; --print-margin-top: -1mm; --print-margin-bottom: 0.000mm; --print-margin-left: 0mm; --print-margin-right: 0.000mm; } :root, ::after, ::before { --print-width: 210.000mm; --print-height: 297.000mm; --print-container-width: 210.000mm; --print-container-height: 297.002mm; --print-margin-top: -2mm; --print-margin-bottom: 0.000mm; --print-margin-left: 0mm; --print-margin-right: 0.000mm; } :root, ::after, ::before { --print-width: 210.000mm; --print-height: 297.000mm; --print-container-width: 210.000mm; --print-container-height: 297.000mm; --print-margin-top: -3mm; --print-margin-bottom: 0.000mm; --print-margin-left: 0mm; --print-margin-right: 0.000mm; } :root, ::after, ::before { --print-width: 210.000mm; --print-height: 297.000mm; --print-container-width: 210.000mm; --print-container-height: 297.000mm; --print-margin-top: -4mm; --print-margin-bottom: 0.000mm; --print-margin-left: 0mm; --print-margin-right: 0.000mm; } :root, ::after, ::before { --print-width: 210.000mm; --print-height: 297.000mm; --print-container-width: 210.000mm; --print-container-height: 297.001mm; --print-margin-top: -5.001mm; --print-margin-bottom: 0.000mm; --print-margin-left: 0mm; --print-margin-right: 0.000mm; } :root, ::after, ::before { --print-width: 210.000mm; --print-height: 297.000mm; --print-container-width: 210.000mm; --print-container-height: 297.000mm; --print-margin-top: -4mm; --print-margin-bottom: 0.000mm; --print-margin-left: 0mm; --print-margin-right: 0.000mm; } :root, ::after, ::before { --print-width: 210.000mm; --print-height: 297.000mm; --print-container-width: 210.000mm; --print-container-height: 297.000mm; --print-margin-top: -3mm; --print-margin-bottom: 0.000mm; --print-margin-left: 0mm; --print-margin-right: 0.000mm; } :root, ::after, ::before { --print-width: 210.000mm; --print-height: 297.000mm; --print-container-width: 210.000mm; --print-container-height: 297.002mm; --print-margin-top: -2mm; --print-margin-bottom: 0.000mm; --print-margin-left: 0mm; --print-margin-right: 0.000mm; } :root, ::after, ::before { --print-width: 210.000mm; --print-height: 297.000mm; --print-container-width: 210.000mm; --print-container-height: 297.001mm; --print-margin-top: -1mm; --print-margin-bottom: 0.000mm; --print-margin-left: 0mm; --print-margin-right: 0.000mm; } :root, ::after, ::before { --print-width: 210.000mm; --print-height: 297.000mm; --print-container-width: 210.000mm; --print-container-height: 297.000mm; --print-margin-top: 0mm; --print-margin-bottom: 0.000mm; --print-margin-left: 0mm; --print-margin-right: 0.000mm; } :root, ::after, ::before { --print-width: 210.000mm; --print-height: 297.000mm; --print-container-width: 210.000mm; --print-container-height: 297.000mm; --print-margin-top: 0mm; --print-margin-bottom: 0.000mm; --print-margin-left: 0mm; --print-margin-right: 0.000mm; } :root { --scale-factor: 0.8999999761581421px; --modal-x: 496px; --modal-y: 165px; }@page { size: 210mm 297mm; margin: 0mm; } @page { size: 210mm 297mm; margin: 0mm; } @page { size: 210mm 297mm; margin: 0mm; } @page { size: 210mm 297mm; margin: 0mm; } @page { size: 210mm 297mm; margin: 1mm 0mm 0mm; } @page { size: 210mm 297mm; margin: 2mm 0mm 0mm; } @page { size: 210mm 297mm; margin: 3mm 0mm 0mm; } @page { size: 210mm 297mm; margin: 4mm 0mm 0mm; } @page { size: 210mm 297mm; margin: 5.001mm 0mm 0mm; } @page { size: 210mm 297mm; margin: 4mm 0mm 0mm; } @page { size: 210mm 297mm; margin: 3mm 0mm 0mm; } @page { size: 210mm 297mm; margin: 2mm 0mm 0mm; } @page { size: 210mm 297mm; margin: 1mm 0mm 0mm; } @page { size: 210mm 297mm; margin: 0mm; } @page { size: 210mm 297mm; margin: 0mm; }",
 "custom_format": 0,
 "disabled": 0,
 "doc_type": "Shop Rent Receipt",
 "docstatus": 0,
 "doctype": "Print Format",
 "font_size": 14,
 "idx": 0,
 "line_breaks": 0,
 "margin_bottom": 15.0,
 "margin_left": 15.0,
 "margin_right": 15.0,
 "margin_top": 15.0,
 "modified": "2024-05-07 19:24:39.925312",
 "modified_by": "Administrator",
 "module": "Airport Shop Management",
 "name": "Rent Receipt",
 "owner": "Administrator",
 "page_number": "Hide",
 "print_designer": 1,
 "print_designer_body": "[{\"id\":\"yMNwYwOxNl\",\"type\":\"text\",\"content\":\"\",\"contenteditable\":true,\"isDynamic\":true,\"isFixedSize\":true,\"dynamicContent\":[{\"doctype\":\"\",\"parentField\":\"\",\"fieldname\":\"name\",\"value\":\"\",\"fieldtype\":\"Document\",\"label\":\"Receipt Number\",\"suffix\":null,\"is_labelled\":true,\"is_static\":false,\"style\":{},\"labelStyle\":{},\"nextLine\":true,\"labelStyleEditing\":false},{\"doctype\":\"\",\"parentField\":\"\",\"fieldname\":\"date\",\"value\":\"\",\"fieldtype\":\"Document\",\"label\":\"Print Date :\",\"suffix\":null,\"is_labelled\":true,\"is_static\":false,\"style\":{},\"labelStyle\":{},\"nextLine\":true},{\"doctype\":\"\",\"parentField\":\"\",\"fieldname\":\"from_date\",\"value\":\"\",\"fieldtype\":\"Date\",\"label\":\"From Date :\",\"suffix\":false,\"is_labelled\":true,\"is_static\":false,\"print_hide\":0,\"style\":{},\"labelStyle\":{},\"nextLine\":true,\"suffixRef\":null,\"labelStyleEditing\":false},{\"doctype\":\"\",\"parentField\":\"\",\"fieldname\":\"to_date\",\"value\":\"\",\"fieldtype\":\"Date\",\"label\":\"To Date :\",\"suffix\":null,\"is_labelled\":true,\"is_static\":false,\"print_hide\":0,\"style\":{},\"labelStyle\":{},\"nextLine\":true,\"labelStyleEditing\":false},{\"doctype\":\"\",\"parentField\":\"\",\"fieldname\":\"tenure\",\"value\":\"\",\"fieldtype\":\"Int\",\"label\":\"Tenure :\",\"suffix\":\"Months\",\"is_labelled\":true,\"is_static\":false,\"print_hide\":0,\"style\":{},\"labelStyle\":{},\"nextLine\":true,\"labelStyleEditing\":false,\"suffixRef\":null},{\"doctype\":\"\",\"parentField\":\"\",\"fieldname\":\"grand_total\",\"value\":\"\",\"fieldtype\":\"Currency\",\"label\":\"Grand Total :\",\"suffix\":null,\"is_labelled\":true,\"is_static\":false,\"print_hide\":0,\"style\":{},\"labelStyle\":{},\"nextLine\":true,\"labelStyleEditing\":false},{\"doctype\":\"\",\"parentField\":\"\",\"fieldname\":\"paid\",\"value\":\"\",\"fieldtype\":\"Check\",\"label\":\"Paid :\",\"suffix\":null,\"is_labelled\":true,\"is_static\":false,\"print_hide\":0,\"style\":{},\"labelStyle\":{},\"nextLine\":true,\"labelStyleEditing\":false},{\"doctype\":\"\",\"parentField\":\"\",\"fieldname\":\"tenant\",\"value\":\"\",\"fieldtype\":\"Data\",\"label\":\"Tenant :\",\"suffix\":null,\"is_labelled\":true,\"is_static\":false,\"print_hide\":0,\"style\":{},\"labelStyle\":{},\"nextLine\":true,\"labelStyleEditing\":false},{\"doctype\":\"Airport Shop\",\"parentField\":\"airport_shop\",\"fieldname\":\"shop_name\",\"value\":\"\",\"fieldtype\":\"Data\",\"label\":\"Shop Name :\",\"suffix\":null,\"is_labelled\":true,\"is_static\":false,\"print_hide\":0,\"style\":{},\"labelStyle\":{},\"nextLine\":true},{\"doctype\":\"Shop Contract Details\",\"parentField\":\"shop_contract_details\",\"fieldname\":\"expiry_date\",\"value\":\"\",\"fieldtype\":\"Date\",\"label\":\"Expiry Date :\",\"suffix\":null,\"is_labelled\":true,\"is_static\":false,\"print_hide\":0,\"style\":{},\"labelStyle\":{},\"nextLine\":true}],\"selectedDynamicText\":null,\"isDraggable\":false,\"isResizable\":false,\"isDropZone\":false,\"startX\":44.23565270996096,\"startY\":141.14043011935942,\"pageX\":627.4930419921875,\"pageY\":372.90639009295313,\"width\":715.9583892822266,\"height\":899.5868835449219,\"styleEditMode\":\"main\",\"labelDisplayStyle\":\"standard\",\"style\":{\"textAlign\":\"center\",\"backgroundColor\":\"#c9ffeb\",\"letterSpacing\":\"3px\"},\"labelStyle\":{\"fontWeight\":\"800\",\"textDecoration\":\"underline\",\"fontFamily\":\"Inconsolata\",\"backgroundColor\":\"#ffffff\",\"borderWidth\":\"0px\",\"paddingTop\":\"0px\",\"paddingBottom\":\"0px\",\"paddingLeft\":\"0px\",\"fontSize\":\"16.00px\",\"lineHeight\":4.25},\"heightType\":\"auto-min-height\",\"classes\":[\"error\"],\"isElementOverlapping\":false}]",
 "print_designer_footer": "[]",
 "print_designer_header": "[{\"id\":\"kUUjAFqCNP\",\"type\":\"image\",\"isDraggable\":false,\"isResizable\":false,\"isDropZone\":false,\"isDynamic\":false,\"image\":{\"name\":\"44e3931273\",\"file_name\":\"spoidermon.jpeg\",\"file_url\":\"/files/spoidermon.jpeg\",\"modified\":\"2024-05-07 18:16:49.815220\"},\"startX\":50.8887939453125,\"startY\":3.5555267333984375,\"pageX\":151.55548095703125,\"pageY\":148.33331298828125,\"width\":156.14953889666413,\"height\":124.25361909685938,\"styleEditMode\":\"main\",\"style\":{},\"classes\":[],\"isElementOverlapping\":false},{\"id\":\"TQJyzVPdbv\",\"type\":\"text\",\"content\":\"\",\"contenteditable\":true,\"isDynamic\":true,\"isFixedSize\":false,\"dynamicContent\":[],\"selectedDynamicText\":null,\"isDraggable\":false,\"isResizable\":false,\"isDropZone\":false,\"startX\":222,\"startY\":8.011811022499998,\"pageX\":761,\"pageY\":122,\"width\":2,\"height\":22.98958396911621,\"styleEditMode\":\"main\",\"labelDisplayStyle\":\"standard\",\"style\":{},\"labelStyle\":{},\"heightType\":\"auto\",\"classes\":[],\"isElementOverlapping\":true}]",
 "print_designer_preview_img": "/private/files/print_designer-rent_receipt-preview.jpg",
 "print_designer_print_format": "{\"header\":[{\"id\":\"PEEHkhLLNw\",\"type\":\"rectangle\",\"DOMRef\":null,\"childrens\":[{\"id\":\"CbPTxUvaNY\",\"type\":\"rectangle\",\"DOMRef\":null,\"childrens\":[{\"id\":\"kUUjAFqCNP\",\"type\":\"image\",\"isDraggable\":false,\"isResizable\":false,\"isDropZone\":false,\"isDynamic\":false,\"image\":{\"name\":\"44e3931273\",\"file_name\":\"spoidermon.jpeg\",\"file_url\":\"/files/spoidermon.jpeg\",\"modified\":\"2024-05-07 18:16:49.815220\"},\"startX\":50.8887939453125,\"startY\":3.5555267333984375,\"pageX\":151.55548095703125,\"pageY\":148.33331298828125,\"width\":156.14953889666413,\"height\":124.25361909685938,\"styleEditMode\":\"main\",\"style\":{},\"classes\":[],\"isElementOverlapping\":false}],\"isDraggable\":false,\"isResizable\":false,\"isDropZone\":false,\"startX\":0,\"startY\":0,\"pageX\":0,\"pageY\":0,\"width\":207.03833284197663,\"height\":127.80914583025782,\"styleEditMode\":\"main\",\"style\":{},\"classes\":[\"relative-column\"],\"layoutType\":\"column\",\"relativeColumn\":true,\"heightType\":\"fixed\"},{\"id\":\"sOsBOqQhsY\",\"type\":\"rectangle\",\"DOMRef\":null,\"childrens\":[{\"id\":\"TQJyzVPdbv\",\"type\":\"text\",\"content\":\"\",\"contenteditable\":true,\"isDynamic\":true,\"isFixedSize\":false,\"dynamicContent\":[],\"selectedDynamicText\":null,\"isDraggable\":false,\"isResizable\":false,\"isDropZone\":false,\"startX\":14.961667158023374,\"startY\":8.011811022499998,\"pageX\":761,\"pageY\":122,\"width\":2,\"height\":22.98958396911621,\"styleEditMode\":\"main\",\"labelDisplayStyle\":\"standard\",\"style\":{},\"labelStyle\":{},\"heightType\":\"auto\",\"classes\":[],\"isElementOverlapping\":true}],\"isDraggable\":false,\"isResizable\":false,\"isDropZone\":false,\"startX\":207.03833284197663,\"startY\":0,\"pageX\":207.03833284197663,\"pageY\":0,\"width\":586.6626671580234,\"height\":127.80914583025782,\"styleEditMode\":\"main\",\"style\":{},\"classes\":[\"relative-column\"],\"layoutType\":\"column\",\"relativeColumn\":true,\"heightType\":\"auto\"}],\"isDraggable\":false,\"isResizable\":false,\"isDropZone\":false,\"startX\":0,\"startY\":0,\"pageX\":50.8887939453125,\"pageY\":0,\"width\":793.701,\"height\":133.3451392695703,\"styleEditMode\":\"main\",\"style\":{},\"classes\":[\"relative-row\"],\"layoutType\":\"row\",\"heightType\":\"auto\"}],\"body\":[{\"id\":\"udGuIdahII\",\"type\":\"rectangle\",\"DOMRef\":null,\"childrens\":[{\"id\":\"yMNwYwOxNl\",\"type\":\"text\",\"content\":\"\",\"contenteditable\":true,\"isDynamic\":true,\"isFixedSize\":true,\"dynamicContent\":[{\"doctype\":\"\",\"parentField\":\"\",\"fieldname\":\"name\",\"value\":\"\",\"fieldtype\":\"Document\",\"label\":\"Receipt Number\",\"suffix\":null,\"is_labelled\":true,\"is_static\":false,\"style\":{},\"labelStyle\":{},\"nextLine\":true,\"labelStyleEditing\":false},{\"doctype\":\"\",\"parentField\":\"\",\"fieldname\":\"date\",\"value\":\"\",\"fieldtype\":\"Document\",\"label\":\"Print Date :\",\"suffix\":null,\"is_labelled\":true,\"is_static\":false,\"style\":{},\"labelStyle\":{},\"nextLine\":true},{\"doctype\":\"\",\"parentField\":\"\",\"fieldname\":\"from_date\",\"value\":\"\",\"fieldtype\":\"Date\",\"label\":\"From Date :\",\"suffix\":false,\"is_labelled\":true,\"is_static\":false,\"print_hide\":0,\"style\":{},\"labelStyle\":{},\"nextLine\":true,\"suffixRef\":null,\"labelStyleEditing\":false},{\"doctype\":\"\",\"parentField\":\"\",\"fieldname\":\"to_date\",\"value\":\"\",\"fieldtype\":\"Date\",\"label\":\"To Date :\",\"suffix\":null,\"is_labelled\":true,\"is_static\":false,\"print_hide\":0,\"style\":{},\"labelStyle\":{},\"nextLine\":true,\"labelStyleEditing\":false},{\"doctype\":\"\",\"parentField\":\"\",\"fieldname\":\"tenure\",\"value\":\"\",\"fieldtype\":\"Int\",\"label\":\"Tenure :\",\"suffix\":\"Months\",\"is_labelled\":true,\"is_static\":false,\"print_hide\":0,\"style\":{},\"labelStyle\":{},\"nextLine\":true,\"labelStyleEditing\":false,\"suffixRef\":null},{\"doctype\":\"\",\"parentField\":\"\",\"fieldname\":\"grand_total\",\"value\":\"\",\"fieldtype\":\"Currency\",\"label\":\"Grand Total :\",\"suffix\":null,\"is_labelled\":true,\"is_static\":false,\"print_hide\":0,\"style\":{},\"labelStyle\":{},\"nextLine\":true,\"labelStyleEditing\":false},{\"doctype\":\"\",\"parentField\":\"\",\"fieldname\":\"paid\",\"value\":\"\",\"fieldtype\":\"Check\",\"label\":\"Paid :\",\"suffix\":null,\"is_labelled\":true,\"is_static\":false,\"print_hide\":0,\"style\":{},\"labelStyle\":{},\"nextLine\":true,\"labelStyleEditing\":false},{\"doctype\":\"\",\"parentField\":\"\",\"fieldname\":\"tenant\",\"value\":\"\",\"fieldtype\":\"Data\",\"label\":\"Tenant :\",\"suffix\":null,\"is_labelled\":true,\"is_static\":false,\"print_hide\":0,\"style\":{},\"labelStyle\":{},\"nextLine\":true,\"labelStyleEditing\":false},{\"doctype\":\"Airport Shop\",\"parentField\":\"airport_shop\",\"fieldname\":\"shop_name\",\"value\":\"\",\"fieldtype\":\"Data\",\"label\":\"Shop Name :\",\"suffix\":null,\"is_labelled\":true,\"is_static\":false,\"print_hide\":0,\"style\":{},\"labelStyle\":{},\"nextLine\":true},{\"doctype\":\"Shop Contract Details\",\"parentField\":\"shop_contract_details\",\"fieldname\":\"expiry_date\",\"value\":\"\",\"fieldtype\":\"Date\",\"label\":\"Expiry Date :\",\"suffix\":null,\"is_labelled\":true,\"is_static\":false,\"print_hide\":0,\"style\":{},\"labelStyle\":{},\"nextLine\":true}],\"selectedDynamicText\":null,\"isDraggable\":false,\"isResizable\":false,\"isDropZone\":false,\"startX\":44.23565270996096,\"startY\":7.795290849789126,\"pageX\":627.4930419921875,\"pageY\":372.90639009295313,\"width\":715.9583892822266,\"height\":899.5868835449219,\"styleEditMode\":\"main\",\"labelDisplayStyle\":\"standard\",\"style\":{\"textAlign\":\"center\",\"backgroundColor\":\"#c9ffeb\",\"letterSpacing\":\"3px\"},\"labelStyle\":{\"fontWeight\":\"800\",\"textDecoration\":\"underline\",\"fontFamily\":\"Inconsolata\",\"backgroundColor\":\"#ffffff\",\"borderWidth\":\"0px\",\"paddingTop\":\"0px\",\"paddingBottom\":\"0px\",\"paddingLeft\":\"0px\",\"fontSize\":\"16.00px\",\"lineHeight\":4.25},\"heightType\":\"auto-min-height\",\"classes\":[\"error\"],\"isElementOverlapping\":false}],\"isDraggable\":false,\"isResizable\":false,\"isDropZone\":false,\"startX\":0,\"startY\":133.3451392695703,\"pageX\":44.23565270996096,\"pageY\":133.3451392695703,\"width\":793.701,\"height\":907.3821743947111,\"styleEditMode\":\"main\",\"style\":{},\"classes\":[\"relative-row\"],\"layoutType\":\"row\",\"heightType\":\"auto-min-height\"}],\"footer\":[]}",
 "print_designer_settings": "{\"page\":{\"height\":1122.52,\"width\":793.701,\"marginTop\":0,\"marginBottom\":0,\"marginLeft\":0,\"marginRight\":0,\"headerHeight\":133.3451392695703,\"footerHeight\":70.01181102250004,\"headerHeightWithMargin\":133.3451392695703,\"footerHeightWithMargin\":70.01181102250004,\"UOM\":\"mm\"},\"pdfPrintDPI\":96,\"globalStyles\":{\"staticText\":{\"isGlobalStyle\":true,\"styleEditMode\":\"main\",\"labelDisplayStyle\":\"standard\",\"type\":\"text\",\"isDynamic\":false,\"mainRuleSelector\":\".staticText\",\"style\":{\"display\":\"inline-block\",\"fontFamily\":\"Inter\",\"fontSize\":\"14px\",\"fontWeight\":400,\"color\":\"#000000\",\"textAlign\":\"left\",\"fontStyle\":\"normal\",\"textDecoration\":\"none\",\"textTransform\":\"none\",\"lineHeight\":1.25,\"letterSpacing\":\"0px\",\"contenteditable\":false,\"border\":\"none\",\"borderWidth\":\"0px\",\"borderColor\":\"#000000\",\"borderStyle\":\"solid\",\"borderRadius\":0,\"backgroundColor\":\"\",\"paddingTop\":\"0px\",\"paddingBottom\":\"0px\",\"paddingLeft\":\"0px\",\"paddingRight\":\"0px\",\"margin\":\"0px\",\"minWidth\":\"0px\",\"minHeight\":\"0px\",\"boxShadow\":\"none\",\"overflow\":\"hidden\",\"overflowWrap\":\"break-word\",\"whiteSpace\":\"normal\",\"userSelect\":\"none\",\"opacity\":1,\"zIndex\":1},\"mainCssRule\":{}},\"dynamicText\":{\"isGlobalStyle\":true,\"styleEditMode\":\"label\",\"labelDisplayStyle\":\"standard\",\"type\":\"text\",\"isDynamic\":true,\"mainRuleSelector\":\".dynamicText\",\"labelRuleSelector\":\".dynamicText .label-text\",\"style\":{\"display\":\"inline-block\",\"fontFamily\":\"Inter\",\"fontSize\":\"14px\",\"fontWeight\":400,\"color\":\"#000000\",\"textAlign\":\"left\",\"fontStyle\":\"normal\",\"textDecoration\":\"none\",\"textTransform\":\"none\",\"lineHeight\":1.25,\"letterSpacing\":\"0px\",\"contenteditable\":false,\"border\":\"none\",\"borderWidth\":\"0px\",\"borderColor\":\"#000000\",\"borderStyle\":\"solid\",\"borderRadius\":0,\"backgroundColor\":\"\",\"paddingTop\":\"0px\",\"paddingBottom\":\"0px\",\"paddingLeft\":\"0px\",\"paddingRight\":\"0px\",\"margin\":\"0px\",\"minWidth\":\"0px\",\"minHeight\":\"0px\",\"boxShadow\":\"none\",\"overflow\":\"hidden\",\"overflowWrap\":\"break-word\",\"whiteSpace\":\"normal\",\"userSelect\":\"none\",\"opacity\":1},\"labelStyle\":{\"fontFamily\":\"Inter\",\"fontSize\":\"14px\",\"fontWeight\":600,\"color\":\"#000000\",\"textAlign\":\"left\",\"fontStyle\":\"normal\",\"textDecoration\":\"none\",\"textTransform\":\"none\",\"lineHeight\":1.25,\"letterSpacing\":\"0px\",\"border\":\"none\",\"borderWidth\":\"0px\",\"borderColor\":\"#000000\",\"borderStyle\":\"solid\",\"borderRadius\":0,\"backgroundColor\":\"\",\"paddingTop\":\"0px\",\"paddingBottom\":\"0px\",\"paddingLeft\":\"0px\",\"paddingRight\":\"0px\",\"margin\":\"0px\",\"minWidth\":\"0px\",\"minHeight\":\"0px\",\"boxShadow\":\"none\",\"whiteSpace\":\"normal\",\"userSelect\":\"none\",\"opacity\":1,\"zIndex\":1},\"mainCssRule\":{},\"labelCssRule\":{}},\"rectangle\":{\"isGlobalStyle\":true,\"styleEditMode\":\"main\",\"type\":\"rectangle\",\"isDynamic\":false,\"mainRuleSelector\":\".rectangle\",\"style\":{\"paddingTop\":\"0px\",\"paddingBottom\":\"0px\",\"paddingLeft\":\"0px\",\"paddingRight\":\"0px\",\"margin\":\"0px\",\"whiteSpace\":\"normal\",\"userSelect\":\"none\",\"minWidth\":\"0px\",\"minHeight\":\"0px\",\"color\":\"#000000\",\"backgroundColor\":\"\",\"border\":\"1px solid black\",\"borderColor\":\"#000000\",\"borderStyle\":\"solid\",\"borderWidth\":\"1px\",\"boxSizing\":\"border-box\",\"outline\":\"none\",\"borderRadius\":0,\"boxShadow\":\"none\",\"opacity\":1,\"zIndex\":0},\"mainCssRule\":{}},\"image\":{\"isGlobalStyle\":true,\"styleEditMode\":\"main\",\"type\":\"image\",\"isDynamic\":false,\"mainRuleSelector\":\".image\",\"style\":{\"display\":\"block\",\"border\":\"none\",\"borderWidth\":\"0px\",\"borderColor\":\"#000000\",\"borderStyle\":\"solid\",\"borderRadius\":0,\"backgroundColor\":\"\",\"paddingTop\":\"0px\",\"paddingBottom\":\"0px\",\"paddingLeft\":\"0px\",\"paddingRight\":\"0px\",\"margin\":\"0px\",\"minWidth\":\"0px\",\"minHeight\":\"0px\",\"boxShadow\":\"none\",\"whiteSpace\":\"normal\",\"userSelect\":\"none\",\"objectFit\":\"scale-down\",\"objectPosition\":\"center center\",\"backgroundSize\":\"contain\",\"backgroundPosition\":\"center center\",\"backgroundRepeat\":\"no-repeat\",\"opacity\":1},\"mainCssRule\":{}},\"barcode\":{\"isGlobalStyle\":true,\"styleEditMode\":\"main\",\"type\":\"barcode\",\"isDynamic\":false,\"mainRuleSelector\":\".barcode\",\"style\":{\"display\":\"block\",\"border\":\"none\",\"borderWidth\":\"0px\",\"borderColor\":\"#000000\",\"borderStyle\":\"solid\",\"borderRadius\":0,\"backgroundColor\":\"\",\"paddingTop\":\"0px\",\"paddingBottom\":\"0px\",\"paddingLeft\":\"0px\",\"paddingRight\":\"0px\",\"margin\":\"0px\",\"minWidth\":\"0px\",\"minHeight\":\"0px\",\"boxShadow\":\"none\",\"whiteSpace\":\"normal\",\"userSelect\":\"none\",\"opacity\":1},\"mainCssRule\":{}},\"table\":{\"isGlobalStyle\":true,\"styleEditMode\":\"main\",\"labelDisplayStyle\":\"standard\",\"type\":\"table\",\"isDynamic\":true,\"mainRuleSelector\":\".printTable td\",\"headerRuleSelector\":\".printTable th\",\"altRuleSelector\":\".printTable tr:nth-child(even) td\",\"labelRuleSelector\":\".printTable .label-text\",\"style\":{\"fontFamily\":\"Inter\",\"fontSize\":\"10px\",\"fontWeight\":400,\"color\":\"#000000\",\"textAlign\":\"left\",\"fontStyle\":\"normal\",\"textDecoration\":\"none\",\"textTransform\":\"none\",\"lineHeight\":1.25,\"letterSpacing\":\"0px\",\"contenteditable\":false,\"border\":\"none\",\"borderWidth\":\"1px\",\"borderColor\":\"#000000\",\"borderStyle\":\"solid\",\"borderRadius\":0,\"backgroundColor\":\"#ffffff\",\"paddingTop\":\"10px\",\"paddingBottom\":\"10px\",\"paddingLeft\":\"10px\",\"paddingRight\":\"10px\",\"margin\":\"0px\",\"minWidth\":\"0px\",\"minHeight\":\"0px\",\"boxShadow\":\"none\",\"overflowWrap\":\"break-word\",\"whiteSpace\":\"normal\",\"userSelect\":\"none\",\"verticalAlign\":\"baseline\",\"opacity\":1},\"labelStyle\":{\"fontFamily\":\"Inter\",\"fontSize\":\"10px\",\"fontWeight\":600,\"color\":\"#000000\",\"textAlign\":\"left\",\"fontStyle\":\"normal\",\"textDecoration\":\"none\",\"textTransform\":\"none\",\"lineHeight\":1.25,\"letterSpacing\":\"0px\",\"border\":\"none\",\"borderWidth\":\"0px\",\"borderColor\":\"#000000\",\"borderStyle\":\"solid\",\"borderRadius\":0,\"backgroundColor\":\"#ffffff\",\"paddingTop\":\"0px\",\"paddingBottom\":\"0px\",\"paddingLeft\":\"0px\",\"paddingRight\":\"0px\",\"margin\":\"0px\",\"minWidth\":\"0px\",\"minHeight\":\"0px\",\"boxShadow\":\"none\",\"whiteSpace\":\"normal\",\"userSelect\":\"none\",\"opacity\":1,\"verticalAlign\":\"baseline\",\"zIndex\":1},\"headerStyle\":{\"fontFamily\":\"Inter\",\"fontSize\":\"11px\",\"fontWeight\":600,\"color\":\"#000000\",\"textAlign\":\"left\",\"fontStyle\":\"normal\",\"textDecoration\":\"none\",\"textTransform\":\"none\",\"lineHeight\":1.25,\"letterSpacing\":\"0px\",\"border\":\"none\",\"borderWidth\":\"1px\",\"borderColor\":\"#000000\",\"borderStyle\":\"solid\",\"borderRadius\":0,\"backgroundColor\":\"#ffffff\",\"paddingTop\":\"10px\",\"paddingBottom\":\"10px\",\"paddingLeft\":\"10px\",\"paddingRight\":\"10px\",\"margin\":\"0px\",\"minWidth\":\"0px\",\"minHeight\":\"0px\",\"boxShadow\":\"none\",\"whiteSpace\":\"normal\",\"userSelect\":\"none\",\"opacity\":1,\"zIndex\":1},\"altStyle\":{},\"mainCssRule\":{},\"labelCssRule\":{},\"headerCssRule\":{},\"altCssRule\":{}}},\"currentPageSize\":\"CUSTOM\",\"isHeaderFooterAuto\":false,\"currentDoc\":\"SRR-07-05-2024-00049\",\"textControlType\":\"dynamic\",\"currentFonts\":[\"Inter\",\"Inconsolata\"],\"printHeaderFonts\":{\"Inter\":{\"weight\":[400,600],\"italic\":[]}},\"printFooterFonts\":null,\"printBodyFonts\":{\"Inter\":{\"weight\":[400],\"italic\":[]},\"Inconsolata\":{\"weight\":[800],\"italic\":[]}},\"userProvidedJinja\":\"\",\"schema_version\":\"1.2.0\"}",
 "print_designer_template_app": "airplane_mode",
 "print_format_builder": 0,
 "print_format_builder_beta": 0,
 "print_format_type": "Jinja",
 "raw_printing": 0,
 "show_section_headings": 0,
 "standard": "Yes"
}